.installed.cfg
.mr.developer.cfg
CHANGES.txt
COPYRIGHT.txt
LICENSE.txt
MANIFEST.in
README.txt
bootstrap.py
buildout.cfg
setup.cfg
setup.py
versions.cfg
src/ztfy/__init__.py
src/ztfy.webapp.egg-info/PKG-INFO
src/ztfy.webapp.egg-info/SOURCES.txt
src/ztfy.webapp.egg-info/dependency_links.txt
src/ztfy.webapp.egg-info/entry_points.txt
src/ztfy.webapp.egg-info/namespace_packages.txt
src/ztfy.webapp.egg-info/not-zip-safe
src/ztfy.webapp.egg-info/requires.txt
src/ztfy.webapp.egg-info/top_level.txt
src/ztfy/webapp/__init__.py
src/ztfy/webapp/webapp_base/__init__.py
src/ztfy/webapp/webapp_base/paste_script_patch.py
src/ztfy/webapp/webapp_base/template.py
src/ztfy/webapp/webapp_base/tests/__init__.py
src/ztfy/webapp/webapp_base/tests/test_webapp.py
src/ztfy/webapp/webapp_base/tests/webapp.txt
src/ztfy/webapp/webapp_base/webapp_template/README.txt_tmpl
src/ztfy/webapp/webapp_base/webapp_template/bootstrap.py
src/ztfy/webapp/webapp_base/webapp_template/buildout.cfg_tmpl
src/ztfy/webapp/webapp_base/webapp_template/debug.ini_tmpl
src/ztfy/webapp/webapp_base/webapp_template/deploy.ini_tmpl
src/ztfy/webapp/webapp_base/webapp_template/setup.py_tmpl
src/ztfy/webapp/webapp_base/webapp_template/etc/apidoc.zcml
src/ztfy/webapp/webapp_base/webapp_template/etc/configure.zcml_tmpl
src/ztfy/webapp/webapp_base/webapp_template/etc/debug.zcml
src/ztfy/webapp/webapp_base/webapp_template/etc/deploy.zcml
src/ztfy/webapp/webapp_base/webapp_template/etc/overrides.zcml
src/ztfy/webapp/webapp_base/webapp_template/etc/security.zcml_tmpl
src/ztfy/webapp/webapp_base/webapp_template/etc/zope-debug.conf_tmpl
src/ztfy/webapp/webapp_base/webapp_template/etc/zope-deploy.conf_tmpl
src/ztfy/webapp/webapp_base/webapp_template/etc/mod_wsgi/+project+.conf_tmpl
src/ztfy/webapp/webapp_base/webapp_template/extends-cache/README.txt
src/ztfy/webapp/webapp_base/webapp_template/src/webapp/__init__.py
src/ztfy/webapp/webapp_base/webapp_template/src/webapp/debug.py
src/ztfy/webapp/webapp_base/webapp_template/src/webapp/startup.py
src/ztfy/webapp/webapp_base/webapp_template/src/webapp/tests/__init__.py
src/ztfy/webapp/webapp_base/webapp_template/src/webapp/tests/ftesting.zcml_tmpl
src/ztfy/webapp/webapp_base/webapp_template/src/webapp/tests/tests.py_tmpl
src/ztfy/webapp/webapp_base/webapp_template/var/filestorage/README.txt
