Metadata-Version: 1.1
Name: ztfy.webapp
Version: 1.1.5
Summary: ZTFY web application template
Home-page: http://www.ztfy.org
Author: Thierry Florac
Author-email: tflorac@ulthar.net
License: ZPL
Platform: UNKNOWN
Classifier: Development Status :: 5 - Production/Stable
Classifier: Environment :: Web Environment
Classifier: Intended Audience :: Developers
Classifier: License :: OSI Approved :: Zope Public License
Classifier: Programming Language :: Python
Classifier: Framework :: Zope3
Classifier: Topic :: Internet :: WWW/HTTP
Classifier: Topic :: Internet :: WWW/HTTP :: WSGI
